HPrice/HPrice.py
HPrice/__init__.py
HPrice-0.0.1.dist-info/LICENSE
HPrice-0.0.1.dist-info/METADATA
HPrice-0.0.1.dist-info/WHEEL
HPrice-0.0.1.dist-info/top_level.txt
HPrice-0.0.1.dist-info/RECORD
