Metadata-Version: 2.1
Name: HPrice
Version: 0.0.1
Summary: a package that makes HPrice data from simple OHLC candlestick data
Home-page: https://github.com/MrHbogart/HPrice
Author: MrHBogart
License: UNKNOWN
Platform: UNKNOWN
Classifier: Programming Language :: Python :: 3
Classifier: License :: OSI Approved :: MIT License
Classifier: Operating System :: OS Independent
Requires-Python: >=3.7
License-File: LICENSE
